ChangeLog
MANIFEST.in
README
README.md
setup.py
django_biblio.egg-info/PKG-INFO
django_biblio.egg-info/SOURCES.txt
django_biblio.egg-info/dependency_links.txt
django_biblio.egg-info/requires.txt
django_biblio.egg-info/top_level.txt
djbiblio/__init__.py
djbiblio/admin.py
djbiblio/models.py
djbiblio/tests.py
djbiblio/views.py
djbiblio/migrations/0001_initial.py
djbiblio/migrations/__init__.py