Metadata-Version: 1.1
Name: django-biblio
Version: 0.2
Summary: django app for storing bibliographical references
Home-page: https://bitbucket.org/grochmal/django-biblio
Author: Michal Grochmal
Author-email: grochmal at member dot fsf dot org
License: GNU General Public License, version 3 or later
Platform: UNKNOWN
Classifier: License :: OSI Approved :: GNU General Public License v3 or later (GPLv3+)
Classifier: Development Status :: 3 - Alpha
Classifier: Environment :: Web Environment
Classifier: Framework :: Django
Classifier: Intended Audience :: Science/Research
Classifier: Operating System :: OS Independent
Classifier: Programming Language :: Python
Classifier: Topic :: Text Processing :: Markup :: LaTeX
